clearcoreai/__init__.py
clearcoreai/orchestrator/__init__.py
clearcoreai/orchestrator/agent_manager.py
clearcoreai/orchestrator/license_manager.py
clearcoreai/orchestrator/main.py
clearcoreai/orchestrator/resource_manager.py
ClearCoreAIProject-0.3.1.dist-info/LICENSE
ClearCoreAIProject-0.3.1.dist-info/METADATA
ClearCoreAIProject-0.3.1.dist-info/WHEEL
ClearCoreAIProject-0.3.1.dist-info/top_level.txt
ClearCoreAIProject-0.3.1.dist-info/RECORD
