Metadata-Version: 2.1
Name: ClearCoreAIProject
Version: 0.3.1
Summary: ClearCoreAI - Transparent and robust orchestration of modular AI agents
Home-page: https://github.com/ClearCoreAI/clearcoreai
Author: Olivier Hays
Author-email: olivier@clearcore.ai
License: MIT
License-File: LICENSE
